{
  "swagger": "2.0",
  "info": {
    "version": "2015-01-14-preview",
    "title": "IntuneResourceManagementClient",
    "description": "Microsoft.Intune Resource provider Api features in the swagger-2.0 specification"
  },
  "host": "management.azure.com",
  "schemes": [
    "https"
  ],
  "paths": {
    "/providers/Microsoft.Intune/locations/{hostName}/flaggedUsers/{userName}": {
      "get": {
        "description": "Returns Intune flagged user details",
        "operationId": "GetMAMFlaggedUserByName",
        "produces": [
          "application/json"
        ],
        "parameters": [
          {
            "name": "hostName",
            "in": "path",
            "description": "Location hostName for the tenant",
            "required": true,
            "type": "string"
          },
          {
            "name": "userName",
            "in": "path",
            "description": "Flagged userName",
            "required": true,
            "type": "string"
          },
          {
            "$ref": "#/parameters/ApiVersionParameter"
          },
          {
            "name": "$select",
            "in": "query",
            "required": false,
            "type": "string",
            "description": "select specific fields in entity."
          }
        ],
        "responses": {
          "200": {
            "description": "Flagged user details in response",
            "schema": {
              "$ref": "#/definitions/FlaggedUser"
            }
          },
          "default": {
            "description": "unexpected error",
            "schema": {
              "$ref": "#/definitions/Error"
            }
          }
        },
        "consumes": [
          "application/json"
        ]
      }
    }
  },
  "definitions": null,
  "parameters": {
    "ApiVersionParameter": {
      "name": "api-version",
      "in": "query",
      "required": true,
      "type": "string",
      "description": "Service Api Version."
    }
  },
  "x-internal-toc-name": "Get MAM Flagged User By Name",
  "x-internal-split-type": "OperationGroup",
  "x-internal-split-members": [
    {
      "displayName": "Add App For MAM Policy",
      "relativePath": "Android/AddAppForMAMPolicy"
    },
    {
      "displayName": "Add Group For MAM Policy",
      "relativePath": "Android/AddGroupForMAMPolicy"
    },
    {
      "displayName": "Create Or Update MAM Policy",
      "relativePath": "Android/CreateOrUpdateMAMPolicy"
    },
    {
      "displayName": "Delete App For MAM Policy",
      "relativePath": "Android/DeleteAppForMAMPolicy"
    },
    {
      "displayName": "Delete Group For MAM Policy",
      "relativePath": "Android/DeleteGroupForMAMPolicy"
    },
    {
      "displayName": "Delete MAM Policy",
      "relativePath": "Android/DeleteMAMPolicy"
    },
    {
      "displayName": "Get App For MAM Policy",
      "relativePath": "Android/GetAppForMAMPolicy"
    },
    {
      "displayName": "Get Groups For MAM Policy",
      "relativePath": "Android/GetGroupsForMAMPolicy"
    },
    {
      "displayName": "Get MAM Policies",
      "relativePath": "Android/GetMAMPolicies"
    },
    {
      "displayName": "Get MAM Policy By Name",
      "relativePath": "Android/GetMAMPolicyByName"
    },
    {
      "displayName": "Patch MAM Policy",
      "relativePath": "Android/PatchMAMPolicy"
    }
  ]
}